avalan/__init__.py
avalan/agent/__init__.py
avalan/agent/engine.py
avalan/agent/loader.py
avalan/agent/orchestrator/__init__.py
avalan/agent/orchestrator/orchestrators/default.py
avalan/agent/orchestrator/orchestrators/json.py
avalan/agent/orchestrator/orchestrators/reasoning/cot.py
avalan/agent/orchestrator/orchestrators/reasoning/parser.py
avalan/agent/orchestrator/response/__init__.py
avalan/agent/orchestrator/response/orchestrator_response.py
avalan/agent/renderer.py
avalan/agent/templates/agent.md
avalan/agent/templates/agent_json.md
avalan/agent/templates/blueprint.toml
avalan/agent/templates/reasoning/cot.md
avalan/cli/__init__.py
avalan/cli/__main__.py
avalan/cli/commands/__init__.py
avalan/cli/commands/agent.py
avalan/cli/commands/cache.py
avalan/cli/commands/deploy.py
avalan/cli/commands/memory.py
avalan/cli/commands/model.py
avalan/cli/commands/tokenizer.py
avalan/cli/download.py
avalan/cli/theme/__init__.py
avalan/cli/theme/fancy.py
avalan/compat.py
avalan/deploy/__init__.py
avalan/deploy/aws.py
avalan/entities.py
avalan/event/__init__.py
avalan/event/manager.py
avalan/filters.py
avalan/flow/__init__.py
avalan/flow/connection.py
avalan/flow/flow.py
avalan/flow/manager.py
avalan/flow/node.py
avalan/memory/__init__.py
avalan/memory/manager.py
avalan/memory/partitioner/__init__.py
avalan/memory/partitioner/code.py
avalan/memory/partitioner/text.py
avalan/memory/permanent/__init__.py
avalan/memory/permanent/elasticsearch/__init__.py
avalan/memory/permanent/elasticsearch/message.py
avalan/memory/permanent/elasticsearch/raw.py
avalan/memory/permanent/migrations/pgsql/down/00001-messages-down.sql
avalan/memory/permanent/migrations/pgsql/down/00002-reasoning-graphs-down.sql
avalan/memory/permanent/migrations/pgsql/up/00001-messages-up.sql
avalan/memory/permanent/migrations/pgsql/up/00002-reasoning-graphs-up.sql
avalan/memory/permanent/pgsql/__init__.py
avalan/memory/permanent/pgsql/message.py
avalan/memory/permanent/pgsql/raw.py
avalan-1.3.10.dist-info/METADATA
avalan-1.3.10.dist-info/WHEEL
avalan-1.3.10.dist-info/entry_points.txt
avalan-1.3.10.dist-info/licenses/LICENSE
avalan-1.3.10.dist-info/RECORD
