Metadata-Version: 2.4
Name: avalan
Version: 1.3.10
Summary: Multi-backend, multi-modal micro-framework for AI agent development, orchestration, and deployment
License: MIT
License-File: LICENSE
Author: The Avalan Team
Author-email: avalan@avalan.ai
Requires-Python: >=3.11,<3.13
Classifier: Development Status :: 4 - Beta
Classifier: Intended Audience :: Developers
Classifier: Intended Audience :: Education
Classifier: Intended Audience :: Science/Research
Classifier: Topic :: Software Development :: Libraries
Classifier: Topic :: Scientific/Engineering :: Artificial Intelligence
Classifier: License :: OSI Approved :: MIT License
Classifier: Programming Language :: Python :: 3.11
Classifier: Operating System :: OS Independent
Provides-Extra: agent
Provides-Extra: all
Provides-Extra: apple
Provides-Extra: audio
Provides-Extra: cpu
Provides-Extra: memory
Provides-Extra: mlx
Provides-Extra: nvidia
Provides-Extra: quantization
Provides-Extra: secrets
Provides-Extra: server
Provides-Extra: test
Provides-Extra: tool
Provides-Extra: translation
Provides-Extra: vendors
Provides-Extra: vision
Provides-Extra: vllm
Requires-Dist: RestrictedPython (==8.0) ; extra == "all"
Requires-Dist: RestrictedPython (==8.0) ; extra == "test"
Requires-Dist: RestrictedPython (==8.0) ; extra == "tool"
Requires-Dist: SQLAlchemy (==2.0.43) ; extra == "all"
Requires-Dist: SQLAlchemy (==2.0.43) ; extra == "test"
Requires-Dist: SQLAlchemy (==2.0.43) ; extra == "tool"
Requires-Dist: a2a-sdk (==0.3.6) ; extra == "all"
Requires-Dist: a2a-sdk (==0.3.6) ; extra == "server"
Requires-Dist: a2a-sdk (==0.3.6) ; extra == "test"
Requires-Dist: accelerate (==1.9.0) ; extra == "all"
Requires-Dist: accelerate (==1.9.0) ; extra == "cpu"
Requires-Dist: aiomysql (==0.2.0) ; extra == "all"
Requires-Dist: aiomysql (==0.2.0) ; extra == "test"
Requires-Dist: aiomysql (==0.2.0) ; extra == "tool"
Requires-Dist: anthropic (==0.61.0) ; extra == "all"
Requires-Dist: anthropic (==0.61.0) ; extra == "vendors"
Requires-Dist: asyncpg (==0.30.0) ; extra == "all"
Requires-Dist: asyncpg (==0.30.0) ; extra == "test"
Requires-Dist: asyncpg (==0.30.0) ; extra == "tool"
Requires-Dist: beautifulsoup4 (==4.14.2) ; extra == "all"
Requires-Dist: beautifulsoup4 (==4.14.2) ; extra == "memory"
Requires-Dist: beautifulsoup4 (==4.14.2) ; extra == "test"
Requires-Dist: bitsandbytes (==0.46.1) ; extra == "nvidia"
Requires-Dist: bitsandbytes (==0.46.1) ; extra == "quantization"
Requires-Dist: boto3 (==1.40.3) ; extra == "all"
Requires-Dist: boto3 (==1.40.3) ; extra == "memory"
Requires-Dist: boto3 (==1.40.3) ; extra == "secrets"
Requires-Dist: boto3 (==1.40.3) ; extra == "test"
Requires-Dist: diffusers (==0.34.0) ; extra == "all"
Requires-Dist: diffusers (==0.34.0) ; extra == "test"
Requires-Dist: diffusers (==0.34.0) ; extra == "vision"
Requires-Dist: elasticsearch (==9.1.0) ; extra == "all"
Requires-Dist: elasticsearch (==9.1.0) ; extra == "memory"
Requires-Dist: elasticsearch (==9.1.0) ; extra == "test"
Requires-Dist: faiss-cpu (==1.11.0.post1) ; extra == "all"
Requires-Dist: faiss-cpu (==1.11.0.post1) ; extra == "memory"
Requires-Dist: faiss-cpu (==1.11.0.post1) ; extra == "test"
Requires-Dist: fastapi (==0.116.1) ; extra == "all"
Requires-Dist: fastapi (==0.116.1) ; extra == "server"
Requires-Dist: fastapi (==0.116.1) ; extra == "test"
Requires-Dist: google-genai (==1.28.0) ; extra == "all"
Requires-Dist: google-genai (==1.28.0) ; extra == "vendors"
Requires-Dist: huggingface-hub (==0.34.3) ; extra == "all"
Requires-Dist: huggingface-hub (==0.34.3) ; extra == "test"
Requires-Dist: humanize (==4.12.3)
Requires-Dist: imageio (==2.37.0) ; extra == "all"
Requires-Dist: imageio (==2.37.0) ; extra == "test"
Requires-Dist: imageio (==2.37.0) ; extra == "vision"
Requires-Dist: imageio-ffmpeg (==0.6.0) ; extra == "all"
Requires-Dist: imageio-ffmpeg (==0.6.0) ; extra == "test"
Requires-Dist: imageio-ffmpeg (==0.6.0) ; extra == "vision"
Requires-Dist: jinja2 (==3.1.6) ; extra == "agent"
Requires-Dist: jinja2 (==3.1.6) ; extra == "all"
Requires-Dist: keyring (==25.6.0) ; extra == "all"
Requires-Dist: keyring (==25.6.0) ; extra == "secrets"
Requires-Dist: keyring (==25.6.0) ; extra == "test"
Requires-Dist: litellm (==1.75.0) ; extra == "all"
Requires-Dist: litellm (==1.75.0) ; extra == "test"
Requires-Dist: litellm (==1.75.0) ; extra == "vendors"
Requires-Dist: markdownify (==1.1.0) ; extra == "all"
Requires-Dist: markdownify (==1.1.0) ; extra == "memory"
Requires-Dist: markdownify (==1.1.0) ; extra == "test"
Requires-Dist: markitdown[pdf] (==0.1.2) ; extra == "all"
Requires-Dist: markitdown[pdf] (==0.1.2) ; extra == "memory"
Requires-Dist: markitdown[pdf] (==0.1.2) ; extra == "test"
Requires-Dist: mcp (==1.12.3) ; extra == "all"
Requires-Dist: mcp (==1.12.3) ; extra == "server"
Requires-Dist: mcp (==1.12.3) ; extra == "test"
Requires-Dist: mlx (==0.28.0) ; extra == "apple"
Requires-Dist: mlx (==0.28.0) ; extra == "mlx"
Requires-Dist: mlx (==0.28.0) ; extra == "test"
Requires-Dist: mlx-lm (==0.26.3) ; extra == "apple"
Requires-Dist: mlx-lm (==0.26.3) ; extra == "mlx"
Requires-Dist: mlx-lm (==0.26.3) ; extra == "test"
Requires-Dist: openai (==1.90.0) ; extra == "all"
Requires-Dist: openai (==1.90.0) ; extra == "test"
Requires-Dist: openai (==1.90.0) ; extra == "vendors"
Requires-Dist: opencv-python (==4.12.0.88) ; extra == "all"
Requires-Dist: opencv-python (==4.12.0.88) ; extra == "test"
Requires-Dist: opencv-python (==4.12.0.88) ; extra == "vision"
Requires-Dist: packaging (==25.0)
Requires-Dist: pandas (==2.3.1)
Requires-Dist: pgvector (==0.4.1) ; extra == "all"
Requires-Dist: pgvector (==0.4.1) ; extra == "memory"
Requires-Dist: pgvector (==0.4.1) ; extra == "test"
Requires-Dist: pillow (==11.3.0) ; extra == "all"
Requires-Dist: pillow (==11.3.0) ; extra == "test"
Requires-Dist: pillow (==11.3.0) ; extra == "vendors"
Requires-Dist: pillow (==11.3.0) ; extra == "vision"
Requires-Dist: playwright (==1.54.0) ; extra == "all"
Requires-Dist: playwright (==1.54.0) ; extra == "test"
Requires-Dist: playwright (==1.54.0) ; extra == "tool"
Requires-Dist: protobuf (==6.31.1) ; extra == "all"
Requires-Dist: protobuf (==6.31.1) ; extra == "translation"
Requires-Dist: psycopg[binary,pool] (==3.2.9) ; extra == "all"
Requires-Dist: psycopg[binary,pool] (==3.2.9) ; extra == "memory"
Requires-Dist: psycopg[binary,pool] (==3.2.9) ; extra == "test"
Requires-Dist: pydantic (==2.11.7) ; extra == "all"
Requires-Dist: pydantic (==2.11.7) ; extra == "server"
Requires-Dist: pydantic (==2.11.7) ; extra == "test"
Requires-Dist: pypdf (==6.1.1) ; extra == "all"
Requires-Dist: pypdf (==6.1.1) ; extra == "memory"
Requires-Dist: pypdf (==6.1.1) ; extra == "test"
Requires-Dist: pytest (==8.4.1) ; extra == "all"
Requires-Dist: pytest (==8.4.1) ; extra == "test"
Requires-Dist: pytest-cov (==6.2.1) ; extra == "all"
Requires-Dist: pytest-cov (==6.2.1) ; extra == "test"
Requires-Dist: rich (==14.1.0)
Requires-Dist: sentence-transformers (==5.1.0) ; extra == "all"
Requires-Dist: sentence-transformers (==5.1.0) ; extra == "memory"
Requires-Dist: sentencepiece (==0.2.0) ; extra == "all"
Requires-Dist: sentencepiece (==0.2.0) ; extra == "translation"
Requires-Dist: soundfile (==0.13.1) ; extra == "all"
Requires-Dist: soundfile (==0.13.1) ; extra == "audio"
Requires-Dist: sqlglot (==27.20.0) ; extra == "all"
Requires-Dist: sqlglot (==27.20.0) ; extra == "test"
Requires-Dist: sqlglot (==27.20.0) ; extra == "tool"
Requires-Dist: sympy (==1.14.0) ; extra == "all"
Requires-Dist: sympy (==1.14.0) ; extra == "test"
Requires-Dist: sympy (==1.14.0) ; extra == "tool"
Requires-Dist: tiktoken (==0.10.0) ; extra == "all"
Requires-Dist: tiktoken (==0.10.0) ; extra == "test"
Requires-Dist: tiktoken (==0.10.0) ; extra == "translation"
Requires-Dist: tiktoken (==0.10.0) ; extra == "vendors"
Requires-Dist: torch (==2.7.1)
Requires-Dist: torchaudio (==2.7.1) ; extra == "all"
Requires-Dist: torchaudio (==2.7.1) ; extra == "audio"
Requires-Dist: torchaudio (==2.7.1) ; extra == "test"
Requires-Dist: torchvision (==0.22.1) ; extra == "all"
Requires-Dist: torchvision (==0.22.1) ; extra == "vision"
Requires-Dist: transformers (==4.55.0)
Requires-Dist: tree-sitter (==0.25.1) ; extra == "all"
Requires-Dist: tree-sitter (==0.25.1) ; extra == "memory"
Requires-Dist: tree-sitter (==0.25.1) ; extra == "test"
Requires-Dist: tree-sitter-python (==0.23.6) ; extra == "all"
Requires-Dist: tree-sitter-python (==0.23.6) ; extra == "memory"
Requires-Dist: tree-sitter-python (==0.23.6) ; extra == "test"
Requires-Dist: uvicorn (==0.35.0) ; extra == "all"
Requires-Dist: uvicorn (==0.35.0) ; extra == "server"
Requires-Dist: vllm (==0.10.0) ; extra == "nvidia"
Requires-Dist: vllm (==0.10.0) ; extra == "vllm"
Requires-Dist: youtube-transcript-api (==1.2.2) ; extra == "all"
Requires-Dist: youtube-transcript-api (==1.2.2) ; extra == "tool"
Project-URL: Bug Tracker, https://github.com/avalan-ai/avalan/issues
Project-URL: Documentation, https://github.com/avalan-ai/avalan#readme
Project-URL: Homepage, https://avalan.ai
Project-URL: Repository, https://github.com/avalan-ai/avalan
